{
  "<%sW_REP_MAX_2ND_F>アラハギーロエリア": "<%sW_REP_MAX_2ND_F>アラハギーロエリア",
  "<%sW_REP_MAX_2ND_F>エテーネエリア": "<%sW_REP_MAX_2ND_F>エテーネエリア",
  "<%sW_REP_MAX_2ND_F>グランゼドーラエリア": "<%sW_REP_MAX_2ND_F>グランゼドーラエリア",
  "<%sW_REP_MAX_2ND_F>ココラタエリア": "<%sW_REP_MAX_2ND_F>ココラタエリア",
  "<%sW_REP_MAX_2ND_F>セレドエリア": "<%sW_REP_MAX_2ND_F>セレドエリア",
  "<%sW_REP_MAX_2ND_F>メルサンディエリア": "<%sW_REP_MAX_2ND_F>メルサンディエリア",
  "<%sW_REP_MAX_2ND_R>アラハギーロエリア": "<%sW_REP_MAX_2ND_R>アラハギーロエリア",
  "<%sW_REP_MAX_2ND_R>エテーネエリア": "<%sW_REP_MAX_2ND_R>エテーネエリア",
  "<%sW_REP_MAX_2ND_R>グランゼドーラエリア": "<%sW_REP_MAX_2ND_R>グランゼドーラエリア",
  "<%sW_REP_MAX_2ND_R>ココラタエリア": "<%sW_REP_MAX_2ND_R>ココラタエリア",
  "<%sW_REP_MAX_2ND_R>セレドエリア": "<%sW_REP_MAX_2ND_R>セレドエリア",
  "<%sW_REP_MAX_2ND_R>メルサンディエリア": "<%sW_REP_MAX_2ND_R>メルサンディエリア",
  "その他のエリア": "その他のエリア",
  "アグラニエリア": "アグラニエリア",
  "アズランエリア": "アズランエリア",
  "アルウェーンエリア": "アルウェーンエリア",
  "ウルベア帝国エリア": "ウルベア帝国エリア",
  "エテーネ王国エリア": "エテーネ王国エリア",
  "オルセコ王国エリア": "オルセコ王国エリア",
  "オルフェアエリア": "オルフェアエリア",
  "カミハルムイエリア": "カミハルムイエリア",
  "ガタラエリア": "ガタラエリア",
  "ガートラントエリア": "ガートラントエリア",
  "グレンエリア": "グレンエリア",
  "ゴーラエリア": "ゴーラエリア",
  "ジュレットエリア": "ジュレットエリア",
  "ゼクレスエリア": "ゼクレスエリア",
  "ツスクルエリア": "ツスクルエリア",
  "デスディオエリア": "デスディオエリア",
  "ドルワームエリア": "ドルワームエリア",
  "ネクロデアエリア": "ネクロデアエリア",
  "バルディスタエリア": "バルディスタエリア",
  "ファラザードエリア": "ファラザードエリア",
  "プクレットエリア": "プクレットエリア",
  "マイタウンエリア": "マイタウンエリア",
  "メギストリスエリア": "メギストリスエリア",
  "ラッカランエリア": "ラッカランエリア",
  "ランガーオエリア": "ランガーオエリア",
  "レンドアエリア": "レンドアエリア",
  "レーンエリア": "レーンエリア",
  "ヴェリナードエリア": "ヴェリナードエリア",
  "古グランゼドーラエリア": "古グランゼドーラエリア",
  "大エテーネ島エリア": "大エテーネ島エリア",
  "嵐の領界エリア": "嵐の領界エリア",
  "水の領界エリア": "水の領界エリア",
  "氷の領界エリア": "氷の領界エリア",
  "炎の領界エリア": "炎の領界エリア",
  "狭間の世界エリア過去世界エリア": "狭間の世界エリア過去世界エリア",
  "闇の領界エリア": "闇の領界エリア",
  "魔界辺境エリア": "魔界辺境エリア"
}
